odoo/addons/stock_dynamic_routing_delivery/README.rst
odoo/addons/stock_dynamic_routing_delivery/__init__.py
odoo/addons/stock_dynamic_routing_delivery/__manifest__.py
odoo/addons/stock_dynamic_routing_delivery/i18n/it.po
odoo/addons/stock_dynamic_routing_delivery/i18n/stock_dynamic_routing_delivery.pot
odoo/addons/stock_dynamic_routing_delivery/models/__init__.py
odoo/addons/stock_dynamic_routing_delivery/models/stock_move.py
odoo/addons/stock_dynamic_routing_delivery/models/stock_routing_rule.py
odoo/addons/stock_dynamic_routing_delivery/readme/CONTRIBUTORS.md
odoo/addons/stock_dynamic_routing_delivery/readme/DESCRIPTION.md
odoo/addons/stock_dynamic_routing_delivery/static/description/icon.png
odoo/addons/stock_dynamic_routing_delivery/static/description/index.html
odoo/addons/stock_dynamic_routing_delivery/tests/__init__.py
odoo/addons/stock_dynamic_routing_delivery/tests/test_carrier_propagation.py
odoo/addons/stock_dynamic_routing_delivery/views/stock_routing.xml
odoo_addon_stock_dynamic_routing_delivery-18.0.1.1.0.1.dist-info/METADATA
odoo_addon_stock_dynamic_routing_delivery-18.0.1.1.0.1.dist-info/WHEEL
odoo_addon_stock_dynamic_routing_delivery-18.0.1.1.0.1.dist-info/top_level.txt
odoo_addon_stock_dynamic_routing_delivery-18.0.1.1.0.1.dist-info/RECORD
