Metadata-Version: 2.1
Name: odoo-addon-stock_dynamic_routing_delivery
Version: 18.0.1.1.0.1
Requires-Python: >=3.10
Requires-Dist: odoo-addon-stock_dynamic_routing==18.0.*
Requires-Dist: odoo==18.0.*
Summary: Glue module between stock dynamic routing and delivery
Home-page: https://github.com/OCA/stock-logistics-workflow
License: AGPL-3
Author: Camptocamp, BCIM, Odoo Community Association (OCA)
Author-email: support@odoo-community.org
Classifier: Programming Language :: Python
Classifier: Framework :: Odoo
Classifier: Framework :: Odoo :: 18.0
Classifier: License :: OSI Approved :: GNU Affero General Public License v3
